wanda_api_parameters/__init__.py
wanda_api_parameters/run_yaml.py
wanda_api_parameters/additional_functions/__init__.py
wanda_api_parameters/additional_functions/merge_multiple_pdf.py
wanda_api_parameters/additional_functions/process_data_wanda.py
wanda_api_parameters/additional_functions/process_emptying.py
wanda_api_parameters/additional_functions/process_waterlevel.py
wanda_api_parameters/additional_functions/process_waterlevel_pressure.py
wanda_api_parameters/additional_functions/process_waterlevel_time.py
wanda_api_parameters/additional_functions/set_rigid_column.py
wanda_api_parameters/additional_functions/zip_files.py
wanda_api_parameters/classobjects/__init__.py
wanda_api_parameters/classobjects/configured_dataclasses.py
wanda_api_parameters/classobjects/wanda_parameter.py
wanda_api_parameters/classobjects/wanda_parameter_script.py
wanda_api_parameters/classobjects/wanda_plot.py
wanda_api_parameters/classobjects/wanda_scenario.py
wanda_api_parameters/parameters_api/__init__.py
wanda_api_parameters/parameters_api/config.py
wanda_api_parameters/parameters_api/functions.py
wanda_api_parameters/parameters_api/util.py
wanda_api_parameters-0.2.4.dist-info/LICENSE.txt
wanda_api_parameters-0.2.4.dist-info/METADATA
wanda_api_parameters-0.2.4.dist-info/WHEEL
wanda_api_parameters-0.2.4.dist-info/entry_points.txt
wanda_api_parameters-0.2.4.dist-info/top_level.txt
wanda_api_parameters-0.2.4.dist-info/RECORD
